{
  "name": "Nancy Ferguson",
  "age": 64,
  "address": {
    "street": "Akeco View",
    "city": "Vucidehab",
    "state": "MI",
    "zip": "90586"
  },
  "contact": {
    "phone": "(483) 651-4287",
    "servicePhone": "800384217"
  },
  "birthday": "1981-10-30T23:08:48.021Z",
  "ip": "16.82.102.98",
  "foo": "bar",
  "profile": {
    "about": "Tuj tote kuvulak cidnec ofja gifela dulefala so vepcihew sazhezab uh piva zic apu lamovlir. Nuruk ku jate kalbakge izebu bimounu idag paakueh imegi jut zootoira we ozaso. Nofor su caf couzi uda vejasjog fewdoh zuba ti ezivpun gifpatop vuhju dadawaw wuga bosorah nos wejo. Homcofu opwolo tugalvu jimi ji anohifuti zu wifcah ataju faaza ruwcofole ki wozlep finjumjab gul pa. Uculuvav bivhu pafgomi bakadara ric me wut om ovijufo zeukwe hupwor vur op pib big we. Gev ramub fibed potag tuajego apwitnu ovhigwa ot raponso icinene zef ofi era. Ugmuet po jeihecev ipeguzpo haihhu bojlo lij utukuce momal kuj zoh dogepve ge va sekurok zuk.",
    "bio": "Focos cujawrom ces zahkinov vovu omu ubeneneg te fokuog kik munjechu vafsap tar jiw vigizebu wi ba de. Al ci ninnegnuc kevujafi acugocul ke bi mowog nabuzesu ze deumiged hor labzoz sodriod mot esabi efziw. Lafhom foenake efozaw feti nujdudti ci poc cuwal ig ucumta bajfas oka vecaf mewfohac diwmo. Fapi nauca hop pir itcita ce apa su cancuwwa dumtowfas femleg tumifa maena munzi jumuma ujloofo. Emezuve ubezhi wow rir zawu mebafapi luc lit uni vom at azoicimeg gulob zagrof timmihkag. Lid ju fi dupuvu guhul mifram kewilwu oluonuna zakwi fog ra vittuz rulej ru fa as. Tor zojat estoj bemuka uwoagewe di gen pi ti ovu tafakas taronu ijmus ruvcaj erimhoj."
  },
  "apiKey": "e76394db65a57231f8ddb243969d6ce347d86029a26af25fbc0fc206521fc40b",
  "currency": {
    "code": "MZN",
    "name": "Mozambique Metical"
  }
}