{
  "name": "Susie Warner",
  "age": 42,
  "address": {
    "street": "Dovov Place",
    "city": "Jewusup",
    "state": "VT",
    "zip": "90060"
  },
  "contact": {
    "phone": "(715) 927-4058",
    "servicePhone": "800747422"
  },
  "birthday": "2003-10-19T16:14:13.765Z",
  "ip": "186.48.213.185",
  "foo": "bar",
  "profile": {
    "about": "Iznaw gi wirra pad peje saroiru zocmu mo tivcuwo kap ujice coze fimte nij. Mop kuigi deheg fumevce lizzid efi he zicze pusbes gifajjo ucbukoc head to avuriwa kiwucfan otimofev vuha. Up itlo mamud ped pe ugokizman jinib cehumna egsu hokumva leedumi beje va icienrig ub dal gusboj buzzef. Um wajisdeb sajrirpe lod pud capuda uzdumrod azasedpi ugrujvef nozapu vazvushev tum defwento. Mivu ma uteofodo cusah tadlow hoari muzinrif zid lofro ehakce owe ri ubasoaca. Cemiate consaciz wa vipeja ekisarjud nimva pova bulpoam wu cug gokempej ta zozzif geneuw. Ro mu nuz cakmovok cam podu lu ihuhiz sumomki go edi lafmifari fesrugnic gejcug.",
    "bio": "Tedhuz nav wi le be se oni ube ejeduhat rapuvvo de fi ni ga worap ebtaz. Se sedni zurse apiec tov ve me lemo gu refabzi orrurawi anu taabgi ge tohi gipeffo epudurma fez. Vahtiffij uwovuv itec pub uweboh weob fewcat ar kod zu duguj mur."
  },
  "apiKey": "21c69977c722c2889ee88d7ea87cd157ac67d94a02b80b414e3a941a8ddf0864",
  "currency": {
    "code": "UZS",
    "name": "Uzbekistan Som"
  }
}