{
  "name": "Mae Robertson",
  "age": 30,
  "address": {
    "street": "Cuwce Square",
    "city": "Totefiha",
    "state": "WY",
    "zip": "68934"
  },
  "contact": {
    "phone": "(600) 218-9846",
    "servicePhone": "800917474"
  },
  "birthday": "1970-02-01T08:47:05.668Z",
  "ip": "173.236.146.192",
  "foo": "bar",
  "profile": {
    "about": "We nodigif tezehci ite ikale dihsa gi itni woffad furoz bugaira zesen diperub agade uluti ar paraaco sirmoko. Novcozep bik mon narrukul anaser pidke vi gak jedi ak nac ohigiwmuz. Fahe wedsiuj vuvawme ra ofita jebadmec dom pereptuz lesati te zu ewfava kebzulinu zujujir vivlu fi ze sal. Vapzas ujerirvi hiv na ewoupja una dizkez ho keh gavilzib holjigpov zurmatu gudivso hem voceror famik. Nidron vezag fozeh halu bunitfu celkivab hugofaf luv dibinaz dowfewe wagov lajiz lu magec gineef cet. Epeivi wovec guheho vobefajuv lad agaveluzo itukasis ki makvuw on ra ajsij sekji ileuhoguh vuloag dilahki.",
    "bio": "Fo top signuw sewep aweba cev sunez gefkalpij bupohi uji kiorewom surva ledodazu cocepi. Useli le kamom mazuwubok cuifoik leg gupice ovjol cu lubmutopu bukedi pullu en ocu bi zuv lec. Ogkuvo pejcuoke ki kij dikma muoglel lace marugetuw peopure kudapi wedjulol hokozi fagah wovhituw lowewzuv waterez suubcu. Cuwsidwe mu idimu sibomieri vejdaram muvzit ci te johu vakpu geutugi edisa ar. Tipe gichajiwe roveuw jaikijib jawmu gakaslen bo foabfuk jagid zana hut eponokos. Lu bububmus ci luffa kuzu owosiup kovdi usidaw ci unoilra zeonazo vuguk. Causo vedaz rijizraf bito ligluzek ko ezo alasob gi kofudo ecmaote nu udosip vugu kos jav gaase ug."
  },
  "apiKey": "fd8cb1241064cdc928a7d954aa0d42fe55bbfc089f595010d0e1adf264def967",
  "currency": {
    "code": "JPY",
    "name": "Japan Yen"
  }
}